<Properties StartupConfiguration="{D1260BC2-6524-4066-A948-228C5CB5EAAC}|Default">
  <MonoDevelop.Ide.Workbench />
  <MonoDevelop.Ide.Workspace ActiveConfiguration="Debug" />
  <MonoDevelop.Ide.ItemProperties.listDicMinValue PreferredExecutionTarget="MonoDevelop.Default" />
  <MonoDevelop.Ide.DebuggingService.Breakpoints>
    <BreakpointStore>
      <Breakpoint file="/Users/lind.zhang/github/listDicMinValue/Program.cs" relfile="Program.cs" line="89" column="1" />
    </BreakpointStore>
  </MonoDevelop.Ide.DebuggingService.Breakpoints>
  <MonoDevelop.Ide.DebuggingService.PinnedWatches />
  <MultiItemStartupConfigurations />
</Properties>